flask_authlib_client/__init__.py
flask_authlib_client/extras.py
Flask_Authlib_Client-0.0.1.dist-info/METADATA
Flask_Authlib_Client-0.0.1.dist-info/WHEEL
Flask_Authlib_Client-0.0.1.dist-info/top_level.txt
Flask_Authlib_Client-0.0.1.dist-info/RECORD
