Metadata-Version: 2.1
Name: Flask-Authlib-Client
Version: 0.0.1
Summary: An extension to add support for separate resource server authentication to authlib
Home-page: https://github.com/michaelbukachi/flask-authlib-client
Author: Michael Bukachi
Author-email: michaelbukachi@gmail.com
License: BSD
Keywords: flask authlib
Platform: any
Classifier: Environment :: Web Environment
Classifier: Intended Audience :: Developers
Classifier: License :: OSI Approved :: BSD License
Classifier: Operating System :: OS Independent
Classifier: Programming Language :: Python
Classifier: Topic :: Internet :: WWW/HTTP :: Dynamic Content
Classifier: Topic :: Software Development :: Libraries :: Python Modules
